{
  "[PAD]": 71,
  "[UNK]": 70,
  "|": 25,
  "ँ": 10,
  "ं": 55,
  "ः": 11,
  "अ": 13,
  "आ": 38,
  "इ": 66,
  "ई": 21,
  "उ": 33,
  "ऊ": 68,
  "ऋ": 27,
  "ऍ": 6,
  "ए": 54,
  "ऐ": 64,
  "ऑ": 26,
  "ओ": 57,
  "औ": 53,
  "क": 22,
  "ख": 9,
  "ग": 35,
  "घ": 40,
  "च": 58,
  "छ": 29,
  "ज": 42,
  "झ": 48,
  "ञ": 20,
  "ट": 30,
  "ठ": 31,
  "ड": 14,
  "ढ": 23,
  "ण": 18,
  "त": 44,
  "थ": 45,
  "द": 51,
  "ध": 17,
  "न": 19,
  "प": 63,
  "फ": 5,
  "ब": 65,
  "भ": 46,
  "म": 37,
  "य": 36,
  "र": 15,
  "ल": 69,
  "व": 8,
  "श": 16,
  "ष": 28,
  "स": 47,
  "ह": 56,
  "़": 39,
  "ा": 62,
  "ि": 41,
  "ी": 4,
  "ु": 67,
  "ू": 52,
  "ृ": 49,
  "े": 24,
  "ै": 43,
  "ॉ": 34,
  "ो": 1,
  "ौ": 32,
  "्": 61,
  "क़": 60,
  "ख़": 12,
  "ग़": 0,
  "ज़": 3,
  "ड़": 2,
  "ढ़": 59,
  "फ़": 50,
  "ॠ": 7
}
